README.rst
setup.py
src/evrythng/__init__.py
src/evrythng/assertions.py
src/evrythng/exceptions.py
src/evrythng/utils.py
src/evrythng/entities/__init__.py
src/evrythng/entities/action_types.py
src/evrythng/entities/actions.py
src/evrythng/entities/application_users.py
src/evrythng/entities/applications.py
src/evrythng/entities/collections_.py
src/evrythng/entities/locations.py
src/evrythng/entities/places.py
src/evrythng/entities/products.py
src/evrythng/entities/projects.py
src/evrythng/entities/properties.py
src/evrythng/entities/thngs.py
src/evrythng/extended/__init__.py
src/evrythng/extended/reactor.py
src/python_evrythng.egg-info/PKG-INFO
src/python_evrythng.egg-info/SOURCES.txt
src/python_evrythng.egg-info/dependency_links.txt
src/python_evrythng.egg-info/not-zip-safe
src/python_evrythng.egg-info/requires.txt
src/python_evrythng.egg-info/top_level.txt