Metadata-Version: 1.1
Name: python-evrythng
Version: 0.3.2
Summary: A comprehensive pythonic wrapper around the Evrythng REST API.
Home-page: https://github.com/GooeeIOT/python-evrythng
Author: Gooee LLC
Author-email: lyle@gooee.com
License: MIT
Keywords: wrapper,iot,rest,api,evrythng,client,internet of things,thng
Platform: UNKNOWN
Classifier: Development Status :: 5 - Production/Stable
Classifier: Intended Audience :: Developers
Classifier: Natural Language :: English
Classifier: License :: OSI Approved :: MIT License
Classifier: Operating System :: OS Independent
Classifier: Programming Language :: Python
Classifier: Programming Language :: Python :: 3
Classifier: Programming Language :: Python :: 3.3
Classifier: Programming Language :: Python :: 3.4
Classifier: Programming Language :: Python :: 3.5
Classifier: Programming Language :: Python :: 3.6
Classifier: Programming Language :: Python :: Implementation :: CPython
Classifier: Programming Language :: Python :: Implementation :: PyPy
Classifier: Topic :: Utilities
Classifier: Topic :: Software Development :: Libraries
